mkr/__init__.py
mkr/core/__init__.py
mkr/core/mk.py
mkr/core/mkp.py
mkr/utils/PackInfor.py
mkr/utils/PackOS.py
mkr/utils/PyResturct.py
mkr/utils/Tree.py
mkr/utils/__init__.py
mkr-0.2.1.4.dist-info/METADATA
mkr-0.2.1.4.dist-info/WHEEL
mkr-0.2.1.4.dist-info/top_level.txt
mkr-0.2.1.4.dist-info/RECORD
