Metadata-Version: 2.1
Name: mkr
Version: 0.2.1.4
Summary: MicroKernel based on outer framework as it's inner core. Use python project as plugin.
Home-page: UNKNOWN
Author: Eagle'sBaby
Author-email: 2229066748@qq.com
Maintainer: Eagle'sBaby
Maintainer-email: 2229066748@qq.com
License: Apache Licence 2.0
Keywords: microkernel
Platform: all
Classifier: Programming Language :: Python
Classifier: Programming Language :: Python :: 3
Requires-Python: >=3
Requires-Dist: files3
